torchcomms/__init__.py
torchcomms-0.0.1.dist-info/licenses/LICENSE
torchcomms-0.0.1.dist-info/METADATA
torchcomms-0.0.1.dist-info/WHEEL
torchcomms-0.0.1.dist-info/top_level.txt
torchcomms-0.0.1.dist-info/RECORD
