Metadata-Version: 2.4
Name: torchcomms
Version: 0.0.1
Summary: torchcomms
Author-email: Tristan Rice <rice@fn.lc>
License-Expression: BSD-3-Clause
Project-URL: Homepage, https://github.com/meta-pytorch/torchcomms
Project-URL: Issues, https://github.com/meta-pytorch/torchcomms/issues
Classifier: Programming Language :: Python :: 3
Classifier: Operating System :: OS Independent
Requires-Python: >=3.9
License-File: LICENSE
Dynamic: license-file
